{"1": {"regular_count": 70, "regular_winner": -1, "regular_turns": 10, "regular_board": 62938093720343, "ab_count": 64, "ab_winner": -1, "ab_turns": 10, "ab_board": 62938093720343}, "2": {"regular_count": 1220, "regular_winner": 1, "regular_turns": 31, "regular_board": 29373993030825, "ab_count": 963, "ab_winner": 1, "ab_turns": 31, "ab_board": 29373993030825}, "3": {"regular_count": 7810, "regular_winner": 1, "regular_turns": 33, "regular_board": 173319827092571, "ab_count": 4230, "ab_winner": 1, "ab_turns": 33, "ab_board": 173319827092571}, "4": {"regular_count": 62558, "regular_winner": -1, "regular_turns": 36, "regular_board": 21454757494679, "ab_count": 22141, "ab_winner": -1, "ab_turns": 36, "ab_board": 21454757494679}, "5": {"regular_count": 169812, "regular_winner": 1, "regular_turns": 11, "regular_board": 99903735676, "ab_count": 56397, "ab_winner": 1, "ab_turns": 19, "ab_board": 233097792377}, "6": {"regular_count": 2003130, "regular_winner": -1, "regular_turns": 34, "regular_board": 188894166728691, "ab_count": 247717, "ab_winner": -1, "ab_turns": 30, "ab_board": 188894166083531}, "7": {"regular_count": 11836523, "regular_winner": -1, "regular_turns": 38, "regular_board": 5621003227280, "ab_count": 1131156, "ab_winner": -1, "ab_turns": 38, "ab_board": 5621003227280}, "1": {"regular_count": 70, "regular_winner": -1, "regular_turns": 10, "regular_board": 62938093720343, "ab_count": 70, "ab_winner": -1, "ab_turns": 10, "ab_board": 62938093720343}, "2": {"regular_count": 1220, "regular_winner": 1, "regular_turns": 31, "regular_board": 29373993030825, "ab_count": 967, "ab_winner": 1, "ab_turns": 31, "ab_board": 29373993030825}, "3": {"regular_count": 7810, "regular_winner": 1, "regular_turns": 33, "regular_board": 173319827092571, "ab_count": 4401, "ab_winner": 1, "ab_turns": 33, "ab_board": 173319827092571}, "4": {"regular_count": 62558, "regular_winner": -1, "regular_turns": 36, "regular_board": 21454757494679, "ab_count": 22897, "ab_winner": -1, "ab_turns": 36, "ab_board": 21454757494679}, "5": {"regular_count": 169812, "regular_winner": 1, "regular_turns": 11, "regular_board": 99903735676, "ab_count": 52956, "ab_winner": 1, "ab_turns": 11, "ab_board": 99903735676}, "6": {"regular_count": 2003130, "regular_winner": -1, "regular_turns": 34, "regular_board": 188894166728691, "ab_count": 254400, "ab_winner": -1, "ab_turns": 34, "ab_board": 188894166728691}, "7": {"regular_count": 11836523, "regular_winner": -1, "regular_turns": 38, "regular_board": 5621003227280, "ab_count": 1210585, "ab_winner": -1, "ab_turns": 38, "ab_board": 5621003227280}}